framing/__init__.py
framing/__main__.py
framing/tests/__init__.py
framing/tests/test_1984.py
framing-0.0.1.dist-info/LICENSE.txt
framing-0.0.1.dist-info/METADATA
framing-0.0.1.dist-info/WHEEL
framing-0.0.1.dist-info/top_level.txt
framing-0.0.1.dist-info/RECORD
