Metadata-Version: 2.1
Name: framing
Version: 0.0.1
Summary: framing
Author-email: Johannes <johannes-programming@mailfence.com>
License: The MIT License (MIT)
Project-URL: Documentation, https://pypi.org/project/framing
Project-URL: Download, https://pypi.org/project/framing/#files
Project-URL: Source, https://github.com/johannes-programming/framing
Classifier: License :: OSI Approved :: MIT License
Classifier: Programming Language :: Python
Classifier: Programming Language :: Python :: 3
Classifier: Programming Language :: Python :: 3 :: Only
Requires-Python: >=3.12.4
License-File: LICENSE.txt
